Workbook

Sheet products
A1: product_id | B1: product_name | C1: category | D1: unit_price | E1: unit_cost
A2: 201 | B2: Wireless Mouse | C2: Electronics | D2: 650 | E2: 420
A3: 202 | B3: Keyboard | C3: Electronics | D3: 1200 | E3: 780
A4: 203 | B4: Water Bottle | C4: Home & Kitchen | D4: 350 | E4: 180
A5: 204 | B5: Backpack | C5: Fashion | D5: 1500 | E5: 850
A6: 205 | B6: Running Shoes | C6: Fashion | D6: 2400 | E6: 1450
A7: 206 | B7: Coffee Maker | C7: Home & Kitchen | D7: 3200 | E7: 2200
A8: 207 | B8: Bluetooth Speaker | C8: Electronics | D8: 1800 | E8: 1120
A9: 208 | B9: Desk Lamp | C9: Home & Kitchen | D9: 900 | E9: 510
A10: 209 | B10: T-Shirt | C10: Fashion | D10: 700 | E10: 300
A11: 210 | B11: Power Bank | C11: Electronics | D11: 1400 | E11: 900

Sheet orders
A1: order_id | B1: order_date | C1: customer_id | D1: product_id | E1: quantity | F1: unit_price | G1: unit_cost | H1: discount_pct | I1: order_status | J1: payment_method | K1: revenue | L1: total_cost | M1: profit | N1: category | O1: month
A2: 5001 | B2: 45296 | C2: 1001 | D2: 201 | E2: 2 | F2: =VLOOKUP(D2,products!A:E,4,FALSE) -> 650 | G2: =VLOOKUP(D2,products!A:E,5,FALSE) -> 420 | H2: 0 | I2: Delivered | J2: UPI | K2: =F2*E2 -> 1300 | L2: =G2*E2 -> 840 | M2: =K2-L2 -> 460 | N2: =VLOOKUP(D2,products!A:E,3,FALSE) -> Electronics | O2: =TEXT(B2,"mmm") -> Jan | Q2: count_delivered | R2: 46 | U2: Formula Concept:
A3: 5002 | B3: 45299 | C3: 1002 | D3: 204 | E3: 1 | F3: =VLOOKUP(D3,products!A:E,4,FALSE) -> 1500 | G3: =VLOOKUP(D3,products!A:E,5,FALSE) -> 850 | H3: 0.1 | I3: Delivered | J3: Card | K3: =F3*E3 -> 1500 | L3: =G3*E3 -> 850 | M3: =K3-L3 -> 650 | N3: =VLOOKUP(D3,products!A:E,3,FALSE) -> Fashion | O3: =TEXT(B3,"mmm") -> Jan | Q3: count_cancelled | R3: 1
A4: 5003 | B4: 45306 | C4: 1003 | D4: 203 | E4: 3 | F4: =VLOOKUP(D4,products!A:E,4,FALSE) -> 350 | G4: =VLOOKUP(D4,products!A:E,5,FALSE) -> 180 | H4: 0 | I4: Delivered | J4: Cash | K4: =F4*E4 -> 1050 | L4: =G4*E4 -> 540 | M4: =K4-L4 -> 510 | N4: =VLOOKUP(D4,products!A:E,3,FALSE) -> Home & Kitchen | O4: =TEXT(B4,"mmm") -> Jan | Q4: total _quantity | R4: 96 | U4: Revenue = Unit Price × Quantity = ₹500 × 2 = ₹1,000
A5: 5004 | B5: 45312 | C5: 1004 | D5: 205 | E5: 1 | F5: =VLOOKUP(D5,products!A:E,4,FALSE) -> 2400 | G5: =VLOOKUP(D5,products!A:E,5,FALSE) -> 1450 | H5: 0.15 | I5: Delivered | J5: UPI | K5: =F5*E5 -> 2400 | L5: =G5*E5 -> 1450 | M5: =K5-L5 -> 950 | N5: =VLOOKUP(D5,products!A:E,3,FALSE) -> Fashion | O5: =TEXT(B5,"mmm") -> Jan | U5: Profit = (Unit Price − Unit Cost) × Quantity = (₹500 − ₹300) × 2 = ₹400
A6: 5005 | B6: 45324 | C6: 1005 | D6: 202 | E6: 2 | F6: =VLOOKUP(D6,products!A:E,4,FALSE) -> 1200 | G6: =VLOOKUP(D6,products!A:E,5,FALSE) -> 780 | H6: 0.05 | I6: Delivered | J6: Card | K6: =F6*E6 -> 2400 | L6: =G6*E6 -> 1560 | M6: =K6-L6 -> 840 | N6: =VLOOKUP(D6,products!A:E,3,FALSE) -> Electronics | O6: =TEXT(B6,"mmm") -> Feb | Q6: Total Revenue | R6: =SUM(K2:K48) -> 108450
A7: 5006 | B7: 45331 | C7: 1006 | D7: 206 | E7: 1 | F7: =VLOOKUP(D7,products!A:E,4,FALSE) -> 3200 | G7: =VLOOKUP(D7,products!A:E,5,FALSE) -> 2200 | H7: 0.1 | I7: Delivered | J7: UPI | K7: =F7*E7 -> 3200 | L7: =G7*E7 -> 2200 | M7: =K7-L7 -> 1000 | N7: =VLOOKUP(D7,products!A:E,3,FALSE) -> Home & Kitchen | O7: =TEXT(B7,"mmm") -> Feb | Q7: Total Cost | R7: =SUM(L2:L48) -> 65330
A8: 5007 | B8: 45336 | C8: 1007 | D8: 209 | E8: 4 | F8: =VLOOKUP(D8,products!A:E,4,FALSE) -> 700 | G8: =VLOOKUP(D8,products!A:E,5,FALSE) -> 300 | H8: 0 | I8: Delivered | J8: Cash | K8: =F8*E8 -> 2800 | L8: =G8*E8 -> 1200 | M8: =K8-L8 -> 1600 | N8: =VLOOKUP(D8,products!A:E,3,FALSE) -> Fashion | O8: =TEXT(B8,"mmm") -> Feb | Q8: Total Profit | R8: =SUM(M2:M48) -> 43120
A9: 5008 | B9: 45347 | C9: 1008 | D9: 207 | E9: 2 | F9: =VLOOKUP(D9,products!A:E,4,FALSE) -> 1800 | G9: =VLOOKUP(D9,products!A:E,5,FALSE) -> 1120 | H9: 0.05 | I9: Delivered | J9: Card | K9: =F9*E9 -> 3600 | L9: =G9*E9 -> 2240 | M9: =K9-L9 -> 1360 | N9: =VLOOKUP(D9,products!A:E,3,FALSE) -> Electronics | O9: =TEXT(B9,"mmm") -> Feb | T9: *Simple: | U9: Profit = Revenue − Total Cost
A10: 5009 | B10: 45354 | C10: 1009 | D10: 210 | E10: 1 | F10: =VLOOKUP(D10,products!A:E,4,FALSE) -> 1400 | G10: =VLOOKUP(D10,products!A:E,5,FALSE) -> 900 | H10: 0 | I10: Delivered | J10: UPI | K10: =F10*E10 -> 1400 | L10: =G10*E10 -> 900 | M10: =K10-L10 -> 500 | N10: =VLOOKUP(D10,products!A:E,3,FALSE) -> Electronics | O10: =TEXT(B10,"mmm") -> Mar | U10: Revenue = Unit Price × Quantity
A11: 5010 | B11: 45362 | C11: 1010 | D11: 208 | E11: 2 | F11: =VLOOKUP(D11,products!A:E,4,FALSE) -> 900 | G11: =VLOOKUP(D11,products!A:E,5,FALSE) -> 510 | H11: 0.1 | I11: Delivered | J11: Cash | K11: =F11*E11 -> 1800 | L11: =G11*E11 -> 1020 | M11: =K11-L11 -> 780 | N11: =VLOOKUP(D11,products!A:E,3,FALSE) -> Home & Kitchen | O11: =TEXT(B11,"mmm") -> Mar | U11: Total Cost = unit_cost × quantity
A12: 5011 | B12: 45369 | C12: 1001 | D12: 205 | E12: 1 | F12: =VLOOKUP(D12,products!A:E,4,FALSE) -> 2400 | G12: =VLOOKUP(D12,products!A:E,5,FALSE) -> 1450 | H12: 0.05 | I12: Delivered | J12: Card | K12: =F12*E12 -> 2400 | L12: =G12*E12 -> 1450 | M12: =K12-L12 -> 950 | N12: =VLOOKUP(D12,products!A:E,3,FALSE) -> Fashion | O12: =TEXT(B12,"mmm") -> Mar
A13: 5012 | B13: 45376 | C13: 1002 | D13: 201 | E13: 3 | F13: =VLOOKUP(D13,products!A:E,4,FALSE) -> 650 | G13: =VLOOKUP(D13,products!A:E,5,FALSE) -> 420 | H13: 0 | I13: Delivered | J13: UPI | K13: =F13*E13 -> 1950 | L13: =G13*E13 -> 1260 | M13: =K13-L13 -> 690 | N13: =VLOOKUP(D13,products!A:E,3,FALSE) -> Electronics | O13: =TEXT(B13,"mmm") -> Mar
A14: 5013 | B14: 45384 | C14: 1003 | D14: 204 | E14: 2 | F14: =VLOOKUP(D14,products!A:E,4,FALSE) -> 1500 | G14: =VLOOKUP(D14,products!A:E,5,FALSE) -> 850 | H14: 0.1 | I14: Delivered | J14: Card | K14: =F14*E14 -> 3000 | L14: =G14*E14 -> 1700 | M14: =K14-L14 -> 1300 | N14: =VLOOKUP(D14,products!A:E,3,FALSE) -> Fashion | O14: =TEXT(B14,"mmm") -> Apr
A15: 5014 | B15: 45389 | C15: 1004 | D15: 203 | E15: 5 | F15: =VLOOKUP(D15,products!A:E,4,FALSE) -> 350 | G15: =VLOOKUP(D15,products!A:E,5,FALSE) -> 180 | H15: 0.05 | I15: Delivered | J15: Cash | K15: =F15*E15 -> 1750 | L15: =G15*E15 -> 900 | M15: =K15-L15 -> 850 | N15: =VLOOKUP(D15,products!A:E,3,FALSE) -> Home & Kitchen | O15: =TEXT(B15,"mmm") -> Apr
A16: 5015 | B16: 45397 | C16: 1005 | D16: 207 | E16: 1 | F16: =VLOOKUP(D16,products!A:E,4,FALSE) -> 1800 | G16: =VLOOKUP(D16,products!A:E,5,FALSE) -> 1120 | H16: 0 | I16: Delivered | J16: UPI | K16: =F16*E16 -> 1800 | L16: =G16*E16 -> 1120 | M16: =K16-L16 -> 680 | N16: =VLOOKUP(D16,products!A:E,3,FALSE) -> Electronics | O16: =TEXT(B16,"mmm") -> Apr
A17: 5016 | B17: 45405 | C17: 1006 | D17: 209 | E17: 2 | F17: =VLOOKUP(D17,products!A:E,4,FALSE) -> 700 | G17: =VLOOKUP(D17,products!A:E,5,FALSE) -> 300 | H17: 0.15 | I17: Cancelled | J17: Card | K17: =F17*E17 -> 1400 | L17: =G17*E17 -> 600 | M17: =K17-L17 -> 800 | N17: =VLOOKUP(D17,products!A:E,3,FALSE) -> Fashion | O17: =TEXT(B17,"mmm") -> Apr
A18: 5017 | B18: 45413 | C18: 1007 | D18: 206 | E18: 1 | F18: =VLOOKUP(D18,products!A:E,4,FALSE) -> 3200 | G18: =VLOOKUP(D18,products!A:E,5,FALSE) -> 2200 | H18: 0.05 | I18: Delivered | J18: UPI | K18: =F18*E18 -> 3200 | L18: =G18*E18 -> 2200 | M18: =K18-L18 -> 1000 | N18: =VLOOKUP(D18,products!A:E,3,FALSE) -> Home & Kitchen | O18: =TEXT(B18,"mmm") -> May
A19: 5018 | B19: 45421 | C19: 1008 | D19: 202 | E19: 1 | F19: =VLOOKUP(D19,products!A:E,4,FALSE) -> 1200 | G19: =VLOOKUP(D19,products!A:E,5,FALSE) -> 780 | H19: 0 | I19: Delivered | J19: Card | K19: =F19*E19 -> 1200 | L19: =G19*E19 -> 780 | M19: =K19-L19 -> 420 | N19: =VLOOKUP(D19,products!A:E,3,FALSE) -> Electronics | O19: =TEXT(B19,"mmm") -> May
A20: 5019 | B20: 45429 | C20: 1009 | D20: 208 | E20: 3 | F20: =VLOOKUP(D20,products!A:E,4,FALSE) -> 900 | G20: =VLOOKUP(D20,products!A:E,5,FALSE) -> 510 | H20: 0.1 | I20: Delivered | J20: Cash | K20: =F20*E20 -> 2700 | L20: =G20*E20 -> 1530 | M20: =K20-L20 -> 1170 | N20: =VLOOKUP(D20,products!A:E,3,FALSE) -> Home & Kitchen | O20: =TEXT(B20,"mmm") -> May
A21: 5020 | B21: 45440 | C21: 1010 | D21: 210 | E21: 2 | F21: =VLOOKUP(D21,products!A:E,4,FALSE) -> 1400 | G21: =VLOOKUP(D21,products!A:E,5,FALSE) -> 900 | H21: 0.05 | I21: Delivered | J21: UPI | K21: =F21*E21 -> 2800 | L21: =G21*E21 -> 1800 | M21: =K21-L21 -> 1000 | N21: =VLOOKUP(D21,products!A:E,3,FALSE) -> Electronics | O21: =TEXT(B21,"mmm") -> May
A22: 5021 | B22: 45447 | C22: 1011 | D22: 205 | E22: 2 | F22: =VLOOKUP(D22,products!A:E,4,FALSE) -> 2400 | G22: =VLOOKUP(D22,products!A:E,5,FALSE) -> 1450 | H22: 0.1 | I22: Delivered | J22: Card | K22: =F22*E22 -> 4800 | L22: =G22*E22 -> 2900 | M22: =K22-L22 -> 1900 | N22: =VLOOKUP(D22,products!A:E,3,FALSE) -> Fashion | O22: =TEXT(B22,"mmm") -> Jun
A23: 5022 | B23: 45455 | C23: 1012 | D23: 204 | E23: 1 | F23: =VLOOKUP(D23,products!A:E,4,FALSE) -> 1500 | G23: =VLOOKUP(D23,products!A:E,5,FALSE) -> 850 | H23: 0 | I23: Delivered | J23: UPI | K23: =F23*E23 -> 1500 | L23: =G23*E23 -> 850 | M23: =K23-L23 -> 650 | N23: =VLOOKUP(D23,products!A:E,3,FALSE) -> Fashion | O23: =TEXT(B23,"mmm") -> Jun
... A48: 5047 | B48: 45656 | C48: 1001 | D48: 210 | E48: 2 | F48: =VLOOKUP(D48,products!A:E,4,FALSE) -> 1400 | G48: =VLOOKUP(D48,products!A:E,5,FALSE) -> 900 | H48: 0 | I48: Delivered | J48: UPI | K48: =F48*E48 -> 2800 | L48: =G48*E48 -> 1800 | M48: =K48-L48 -> 1000 | N48: =VLOOKUP(D48,products!A:E,3,FALSE) -> Electronics | O48: =TEXT(B48,"mmm") -> Dec

Sheet Order_Chart
A3: Row Labels | B3: Count of order_id
A4: Cancelled | B4: 1 | M4: #Ab hum analyze karenge ki kitne orders
A5: Delivered | B5: 46 | M5: Delivered aur Cancelled hue hain.
A6: Grand Total | B6: 47
M7: #Business Insight ( useful information / pattern):
M8: “Out of 47 total orders, 46 were delivered and
M9: only 1 order was cancelled.”

Sheet Dashboard
E1: E-Commerce Sales & Profit Analytics
B2: TOTAL REVENUE | F2: TOTAL PROFIT | J2: TOTAL ORDERS | M2: CANCELLED ORDERS
B3: 108450 | F3: 43120 | J3: 47 | M3: 1

Sheet Main_Dashboard
B1: 🛒 | D1: E-Commerce Sales & Profit Analytics Sales • Profit • Orders • Performance | K1: 📈
A4: TOTAL REVENUE | D4: TOTAL PROFIT | G4: TOTAL ORDERS | J4: CANCELLED ORDERS
A5: 108450 | D5: 43120 | G5: 47 | J5: 1
A26: 📈 | E26: Better Insights → Higher Profits | K26: 🛒 E-Commerce Analytics

Sheet Payment_Chart
A3: Row Labels | B3: Count of order_id
A4: Card | B4: 17
A5: Cash | B5: 12
A6: UPI | B6: 18
A7: Grand Total | B7: 47

Sheet Revenue_Chart
A3: Row Labels | B3: Sum of revenue
A4: Jan | B4: 6250
A5: Feb | B5: 12000
A6: Mar | B6: 7550
A7: Apr | B7: 7950
A8: May | B8: 9900
A9: Jun | B9: 11300
A10: Jul | B10: 9000
A11: Aug | B11: 9600
A12: Sep | B12: 8100
A13: Oct | B13: 6600
A14: Nov | B14: 7000
A15: Dec | B15: 13200
A16: Grand Total | B16: 108450

Sheet Profit_Chart
A3: Row Labels | B3: Sum of profit
A4: Jan | B4: 2570
A5: Feb | B5: 4800
A6: Mar | B6: 2920
A7: Apr | B7: 3630
A8: May | B8: 3590
A9: Jun | B9: 4590
A10: Jul | B10: 3110
A11: Aug | B11: 4160
A12: Sep | B12: 3020
A13: Oct | B13: 2570
A14: Nov | B14: 2720
A15: Dec | B15: 5440
A16: Grand Total | B16: 43120

Sheet Category_Wise
A3: Row Labels | B3: Sum of revenue | C3: Sum of profit | E3: Data se kya pata chala?
A4: Electronics | B4: 43550 | C4: 15750 | E4: Highest Revenue: Electronics — ₹43,550
A5: Fashion | B5: 34700 | C5: 15850 | E5: Highest Profit: Fashion — ₹15,850
A6: Home & Kitchen | B6: 30200 | C6: 11520 | E6: Lowest Revenue: Home & Kitchen — ₹30,200
A7: Grand Total | B7: 108450 | C7: 43120 | E7: Lowest Profit: Home & Kitchen — ₹11,520
E8: Dhyan do: jis category ka Revenue sabse zyada hai, zaroori nahi ki uska Profit bhi sabse zyada ho!
